{
   "abstract" : "Reveal HTML document structure in a myriad of colors",
   "author" : [
      "Ron Savage <ron@savage.net.au>"
   ],
   "dynamic_config" : 0,
   "generated_by" : "Module::Build version 0.4211",
   "license" : [
      "artistic_1"
   ],
   "meta-spec" : {
      "url" : "http://search.cpan.org/perldoc?CPAN::Meta::Spec",
      "version" : "2"
   },
   "name" : "HTML-Revelation",
   "prereqs" : {
      "build" : {
         "requires" : {
            "Test::More" : "0"
         }
      },
      "configure" : {
         "requires" : {
            "Module::Build" : "0.38"
         }
      },
      "runtime" : {
         "requires" : {
            "File::Spec" : "0",
            "HTML::Entities::Interpolate" : "0",
            "HTML::Tagset" : "0",
            "HTML::TreeBuilder" : "0",
            "List::Cycle" : "0",
            "accessors::classic" : "0"
         }
      }
   },
   "provides" : {
      "HTML::Revelation" : {
         "file" : "lib/HTML/Revelation.pm",
         "version" : "1.03"
      }
   },
   "release_status" : "stable",
   "resources" : {
      "license" : [
         "http://www.perlfoundation.org/artistic_license_1_0"
      ]
   },
   "version" : "1.03"
}
